odoo/addons/partner_statement/README.rst
odoo/addons/partner_statement/__init__.py
odoo/addons/partner_statement/__manifest__.py
odoo/addons/partner_statement/i18n/ca.po
odoo/addons/partner_statement/i18n/de.po
odoo/addons/partner_statement/i18n/es.po
odoo/addons/partner_statement/i18n/es_AR.po
odoo/addons/partner_statement/i18n/fr.po
odoo/addons/partner_statement/i18n/hr_HR.po
odoo/addons/partner_statement/i18n/it.po
odoo/addons/partner_statement/i18n/nl.po
odoo/addons/partner_statement/i18n/nl_NL.po
odoo/addons/partner_statement/i18n/partner_statement.pot
odoo/addons/partner_statement/i18n/pt.po
odoo/addons/partner_statement/i18n/pt_BR.po
odoo/addons/partner_statement/i18n/ro.po
odoo/addons/partner_statement/readme/CONFIGURE.rst
odoo/addons/partner_statement/readme/CONTRIBUTORS.rst
odoo/addons/partner_statement/readme/DESCRIPTION.rst
odoo/addons/partner_statement/readme/HISTORY.rst
odoo/addons/partner_statement/readme/ROADMAP.rst
odoo/addons/partner_statement/readme/USAGE.rst
odoo/addons/partner_statement/report/__init__.py
odoo/addons/partner_statement/report/activity_statement.py
odoo/addons/partner_statement/report/activity_statement_xlsx.py
odoo/addons/partner_statement/report/outstanding_statement.py
odoo/addons/partner_statement/report/outstanting_statement_xlsx.py
odoo/addons/partner_statement/report/report_statement_common.py
odoo/addons/partner_statement/security/statement_security.xml
odoo/addons/partner_statement/static/description/icon.png
odoo/addons/partner_statement/static/description/index.html
odoo/addons/partner_statement/static/src/scss/layout_statement.scss
odoo/addons/partner_statement/tests/__init__.py
odoo/addons/partner_statement/tests/test_activity_statement.py
odoo/addons/partner_statement/tests/test_outstanding_statement.py
odoo/addons/partner_statement/tests/test_res_config_settings.py
odoo/addons/partner_statement/views/activity_statement.xml
odoo/addons/partner_statement/views/aging_buckets.xml
odoo13_addon_partner_statement-13.0.1.4.0.dist-info/METADATA
odoo13_addon_partner_statement-13.0.1.4.0.dist-info/WHEEL
odoo13_addon_partner_statement-13.0.1.4.0.dist-info/top_level.txt
odoo13_addon_partner_statement-13.0.1.4.0.dist-info/RECORD
